alcedo_pdbc/__init__.cp39-win_amd64.pyd
alcedo_pdbc/config.cp39-win_amd64.pyd
alcedo_pdbc/datalake.cp39-win_amd64.pyd
alcedo_pdbc/datalake_utils.cp39-win_amd64.pyd
alcedo_pdbc/datasets.cp39-win_amd64.pyd
alcedo_pdbc/datawarehouse.cp39-win_amd64.pyd
alcedo_pdbc/datawarehouse_utils.cp39-win_amd64.pyd
alcedo_pdbc/exceptions.cp39-win_amd64.pyd
alcedo_pdbc/mysql_operate.cp39-win_amd64.pyd
alcedo_pdbc/nosql.cp39-win_amd64.pyd
alcedo_pdbc/sql.cp39-win_amd64.pyd
alcedo_pdbc/utils.cp39-win_amd64.pyd
alcedo_pdbc-0.1.20250405.data/scripts/LICENSE
alcedo_pdbc-0.1.20250405.data/scripts/README.md
alcedo_pdbc-0.1.20250405.dist-info/LICENSE
alcedo_pdbc-0.1.20250405.dist-info/METADATA
alcedo_pdbc-0.1.20250405.dist-info/WHEEL
alcedo_pdbc-0.1.20250405.dist-info/top_level.txt
alcedo_pdbc-0.1.20250405.dist-info/RECORD
