Metadata-Version: 2.2
Name: alcedo_pdbc
Version: 0.1.20250405
Home-page: 
Author: ailab100
Author-email: ailab100@163.com
License-File: LICENSE
Requires-Dist: boto3>=1.26.93
Requires-Dist: google-cloud-storage>=2.7.0
Requires-Dist: azure-storage-blob>=12.15.0
Requires-Dist: pandas==2.2.3
Requires-Dist: PyYAML
Requires-Dist: connectorx
Requires-Dist: sqlalchemy==1.4.46
Requires-Dist: snowflake-connector-python
Requires-Dist: mysql-connector-python-rf
Requires-Dist: elasticsearch
Requires-Dist: pymongo
Requires-Dist: fastparquet
Requires-Dist: openpyxl
Requires-Dist: xlrd
Requires-Dist: xlwt
Requires-Dist: minio==7.2.15
Requires-Dist: numpy==1.26.4
Requires-Dist: polars==1.26.0
Requires-Dist: redis==5.2.1
Requires-Dist: dask==2024.8.0
Requires-Dist: dask[dataframe]
Provides-Extra: dev
Requires-Dist: argon2-cffi==23.1.0; extra == "dev"
Requires-Dist: argon2-cffi-bindings==21.2.0; extra == "dev"
Requires-Dist: asn1crypto==1.5.1; extra == "dev"
Requires-Dist: async-timeout==5.0.1; extra == "dev"
Requires-Dist: azure-core==1.32.0; extra == "dev"
Requires-Dist: azure-storage-blob==12.25.1; extra == "dev"
Requires-Dist: boto3==1.37.27; extra == "dev"
Requires-Dist: botocore==1.37.27; extra == "dev"
Requires-Dist: cachetools==5.5.2; extra == "dev"
Requires-Dist: certifi==2025.1.31; extra == "dev"
Requires-Dist: cffi==1.17.1; extra == "dev"
Requires-Dist: charset-normalizer==2.1.1; extra == "dev"
Requires-Dist: click==8.1.8; extra == "dev"
Requires-Dist: cloudpickle==3.1.1; extra == "dev"
Requires-Dist: colorama==0.4.6; extra == "dev"
Requires-Dist: connectorx==0.3.3; extra == "dev"
Requires-Dist: cramjam==2.9.1; extra == "dev"
Requires-Dist: cryptography==40.0.2; extra == "dev"
Requires-Dist: dask==2024.8.0; extra == "dev"
Requires-Dist: dnspython==2.7.0; extra == "dev"
Requires-Dist: dynamo-pandas==1.4.0; extra == "dev"
Requires-Dist: elastic-transport==8.17.1; extra == "dev"
Requires-Dist: elasticsearch==8.17.2; extra == "dev"
Requires-Dist: et_xmlfile==2.0.0; extra == "dev"
Requires-Dist: exceptiongroup==1.2.2; extra == "dev"
Requires-Dist: fastparquet==2024.11.0; extra == "dev"
Requires-Dist: filelock==3.18.0; extra == "dev"
Requires-Dist: fsspec==2025.3.2; extra == "dev"
Requires-Dist: google-api-core==2.24.2; extra == "dev"
Requires-Dist: google-auth==2.38.0; extra == "dev"
Requires-Dist: google-cloud-core==2.4.3; extra == "dev"
Requires-Dist: google-cloud-storage==3.1.0; extra == "dev"
Requires-Dist: google-crc32c==1.7.1; extra == "dev"
Requires-Dist: google-resumable-media==2.7.2; extra == "dev"
Requires-Dist: googleapis-common-protos==1.69.2; extra == "dev"
Requires-Dist: greenlet==3.1.1; extra == "dev"
Requires-Dist: idna==3.10; extra == "dev"
Requires-Dist: importlib_metadata==8.6.1; extra == "dev"
Requires-Dist: iniconfig==2.1.0; extra == "dev"
Requires-Dist: isodate==0.7.2; extra == "dev"
Requires-Dist: jmespath==1.0.1; extra == "dev"
Requires-Dist: locket==1.0.0; extra == "dev"
Requires-Dist: minio==7.2.15; extra == "dev"
Requires-Dist: mysql-connector-python-rf==2.2.2; extra == "dev"
Requires-Dist: numpy==1.26.4; extra == "dev"
Requires-Dist: openpyxl==3.1.5; extra == "dev"
Requires-Dist: oscrypto==1.3.0; extra == "dev"
Requires-Dist: packaging==24.2; extra == "dev"
Requires-Dist: pandas==2.2.3; extra == "dev"
Requires-Dist: partd==1.4.2; extra == "dev"
Requires-Dist: pluggy==1.5.0; extra == "dev"
Requires-Dist: polars==1.26.0; extra == "dev"
Requires-Dist: proto-plus==1.26.1; extra == "dev"
Requires-Dist: protobuf==6.30.2; extra == "dev"
Requires-Dist: pyarrow==19.0.1; extra == "dev"
Requires-Dist: pyasn1==0.6.1; extra == "dev"
Requires-Dist: pyasn1_modules==0.4.2; extra == "dev"
Requires-Dist: pycparser==2.22; extra == "dev"
Requires-Dist: pycryptodome==3.22.0; extra == "dev"
Requires-Dist: pycryptodomex==3.22.0; extra == "dev"
Requires-Dist: PyJWT==2.10.1; extra == "dev"
Requires-Dist: pymongo==4.11.3; extra == "dev"
Requires-Dist: pyOpenSSL==23.2.0; extra == "dev"
Requires-Dist: pytest==8.3.5; extra == "dev"
Requires-Dist: python-dateutil==2.9.0.post0; extra == "dev"
Requires-Dist: python-dotenv==1.1.0; extra == "dev"
Requires-Dist: pytz==2025.2; extra == "dev"
Requires-Dist: PyYAML==6.0.2; extra == "dev"
Requires-Dist: redis==5.2.1; extra == "dev"
Requires-Dist: requests==2.32.3; extra == "dev"
Requires-Dist: rsa==4.9; extra == "dev"
Requires-Dist: s3transfer==0.11.4; extra == "dev"
Requires-Dist: six==1.17.0; extra == "dev"
Requires-Dist: snowflake-connector-python==3.0.2; extra == "dev"
Requires-Dist: SQLAlchemy==1.4.46; extra == "dev"
Requires-Dist: table==0.0.4; extra == "dev"
Requires-Dist: tomli==2.2.1; extra == "dev"
Requires-Dist: toolz==1.0.0; extra == "dev"
Requires-Dist: typing_extensions==4.13.1; extra == "dev"
Requires-Dist: tzdata==2025.2; extra == "dev"
Requires-Dist: urllib3==1.26.20; extra == "dev"
Requires-Dist: xlrd==2.0.1; extra == "dev"
Requires-Dist: xlwt==1.3.0; extra == "dev"
Requires-Dist: zipp==3.21.0; extra == "dev"
Dynamic: author
Dynamic: author-email
Dynamic: provides-extra
Dynamic: requires-dist
